{
  "unversionedId": "attsystem/fight/data",
  "id": "attsystem/fight/data",
  "title": "战斗数据",
  "description": "在开读战斗系统前，你需要了解一下AttributeSystem中的战斗数据",
  "source": "@site/docs/attsystem/fight/data.md",
  "sourceDirName": "attsystem/fight",
  "slug": "/attsystem/fight/data",
  "permalink": "/docs/attsystem/fight/data",
  "draft": false,
  "editUrl": "https://github.com/Skillw/Website/docs/attsystem/fight/data.md",
  "tags": [],
  "version": "current",
  "frontMatter": {
    "title": "战斗数据"
  },
  "sidebar": "main",
  "previous": {
    "title": "战斗系统",
    "permalink": "/docs/category/战斗系统"
  },
  "next": {
    "title": "伤害类型",
    "permalink": "/docs/attsystem/fight/damage-type"
  }
}